Modul_Wrapper/__init__.py
Modul_Wrapper/core_modul.py
modul_wrapper-1.0.8.dist-info/licenses/LICENSE
modul_wrapper-1.0.8.dist-info/METADATA
modul_wrapper-1.0.8.dist-info/WHEEL
modul_wrapper-1.0.8.dist-info/top_level.txt
modul_wrapper-1.0.8.dist-info/RECORD
