Metadata-Version: 2.4
Name: Modul_Wrapper
Version: 1.0.8
Summary: Control Your Library With Dictionary
Home-page: https://github.com/staykimin/Modul-Wrapper
Author: KIMIN
Author-email: staykimin@gmail.com
License: MIT
Project-URL: Documentation, https://github.com/staykimin/Modul-Wrapper
Project-URL: Funding, https://github.com/staykimin/Modul-Wrapper
Project-URL: Say Thanks!, https://saweria.co/staykimin
Project-URL: Source, https://github.com/staykimin/Modul-Wrapper
Project-URL: Tracker, https://github.com/staykimin/Modul-Wrapper/issues
Keywords: Kimin,Modul-Wrapper,J2S
Classifier: Development Status :: 4 - Beta
Classifier: Intended Audience :: Developers
Classifier: Topic :: Utilities
Classifier: License :: OSI Approved :: MIT License
Classifier: Programming Language :: Python :: 3
Classifier: Programming Language :: Python :: 3.7
Classifier: Programming Language :: Python :: 3.8
Classifier: Programming Language :: Python :: 3.9
Classifier: Programming Language :: Python :: 3.10
License-File: LICENSE
Dynamic: author
Dynamic: author-email
Dynamic: classifier
Dynamic: description
Dynamic: description-content-type
Dynamic: home-page
Dynamic: keywords
Dynamic: license
Dynamic: license-file
Dynamic: project-url
Dynamic: summary
